{
    "Iso17.9938": {
        "error": 0.0014063837804047818,
        "error_type": null,
        "filter_outliers_dict": {
            "filter_outliers": false,
            "iterations": 1,
            "std_devs": 2
        },
        "fit": "linear",
        "value": 0.7078697765948727
    },
    "Iso24.9938": {
        "error": 0.0008022575117431082,
        "error_type": null,
        "filter_outliers_dict": {
            "filter_outliers": false,
            "iterations": 1,
            "std_devs": 2
        },
        "fit": "linear",
        "value": 0.23121987012903222
    },
    "Ne21": {
        "error": 8.98713500403424e-05,
        "error_type": "SEM",
        "filter_outliers_dict": {
            "filter_outliers": false,
            "iterations": 1,
            "std_devs": 2
        },
        "fit": "linear",
        "value": 0.0023408313984228813
    }
}