{
    "Ne20": {
        "error": 0.016454626691849272,
        "error_type": "SEM",
        "filter_outliers_dict": {
            "filter_outliers": false,
            "iterations": 0,
            "std_devs": 0,
            "use_standard_deviation_filtering": false
        },
        "fit": "Linear",
        "fn": 300,
        "include_baseline_error": false,
        "n": 300,
        "reviewed": true,
        "value": 1.5315538398982773
    },
    "Ne21": {
        "error": 0.0008572174149856789,
        "error_type": "SEM",
        "filter_outliers_dict": {
            "filter_outliers": false,
            "iterations": 0,
            "std_devs": 0,
            "use_standard_deviation_filtering": false
        },
        "fit": "Linear",
        "fn": 300,
        "include_baseline_error": false,
        "n": 300,
        "reviewed": true,
        "value": 0.004763429052227955
    },
    "Ne22": {
        "error": 0.006758226247272531,
        "error_type": "SEM",
        "filter_outliers_dict": {
            "filter_outliers": false,
            "iterations": 0,
            "std_devs": 0,
            "use_standard_deviation_filtering": false
        },
        "fit": "Linear",
        "fn": 300,
        "include_baseline_error": false,
        "n": 300,
        "reviewed": true,
        "value": 0.2919557531958936
    }
}